setup.py
park_worker_base.egg-info/PKG-INFO
park_worker_base.egg-info/SOURCES.txt
park_worker_base.egg-info/dependency_links.txt
park_worker_base.egg-info/requires.txt
park_worker_base.egg-info/top_level.txt
parkworker/__init__.py
parkworker/const.py
parkworker/monit.py
parkworker/settings_default.py
parkworker/task_processor.py
parkworker/utils.py
parkworker/work.py
parkworker/worker.py
parkworker/asyncio/__init__.py
parkworker/asyncio/monit.py
parkworker/asyncio/task_processor.py
parkworker/asyncio/work.py
parkworker/asyncio/worker.py