Metadata-Version: 1.0
Name: park-worker-base
Version: 0.1.0
Summary: Base logic of workers for park-keeper project.
Home-page: https://github.com/telminov/park-worker-base
Author: Telminov Sergey
Author-email: UNKNOWN
License: The MIT License
Platform: UNKNOWN
